README.md
fealden/__init__.py
fealden/__main__.py
fealden/_rnastructure.py
fealden/_unafold.py
fealden/complex_seed.py
fealden/fealden.py
fealden/fold.py
fealden/node.py
fealden/py.typed
fealden/seed.py
fealden/sensor.py
fealden/structure.py
fealden-0.3.2.dist-info/LICENSE
fealden-0.3.2.dist-info/METADATA
fealden-0.3.2.dist-info/WHEEL
fealden-0.3.2.dist-info/entry_points.txt
fealden-0.3.2.dist-info/top_level.txt
fealden-0.3.2.dist-info/RECORD
